koboldfs
