Metadata-Version: 1.0
Name: koboldfs
Version: 0.3.1
Summary: application-level distributed file system written in Python
Home-page: http://pypi.python.org/pypi/koboldfs
Author: Tranchitella Kft.
Author-email: info@tranchitella.eu
License: GPL 2
Platform: UNKNOWN
Classifier: Development Status :: 4 - Beta
Classifier: Intended Audience :: Developers
Classifier: Intended Audience :: System Administrators
Classifier: License :: DFSG approved
Classifier: License :: OSI Approved :: GNU General Public License (GPL)
Classifier: Programming Language :: Python
Classifier: Topic :: System :: Filesystems
